autoscale_agent/__init__.py
autoscale_agent/agent.py
autoscale_agent/configuration.py
autoscale_agent/middleware/__init__.py
autoscale_agent/middleware/django.py
autoscale_agent/middleware/flask.py
autoscale_agent/util.py
autoscale_agent/web_dispatcher.py
autoscale_agent/worker_dispatcher.py
autoscale_agent/worker_dispatchers.py
autoscale_agent/worker_server.py
autoscale_agent/worker_servers.py
autoscale_agent-0.2.1.dist-info/LICENSE
autoscale_agent-0.2.1.dist-info/METADATA
autoscale_agent-0.2.1.dist-info/WHEEL
autoscale_agent-0.2.1.dist-info/RECORD
