Metadata-Version: 2.1
Name: autoscale-agent
Version: 0.2.1
Summary: Provides Autoscale.app with the necessary metrics for autoscaling web and worker processes
Home-page: https://autoscale.app
License: MIT
Keywords: agent,middleware,autoscale,render,web,worker,queue,job
Author: Michael R. van Rooijen
Author-email: support@autoscale.app
Requires-Python: >=3.8,<3.12
Classifier: Development Status :: 4 - Beta
Classifier: Intended Audience :: Developers
Classifier: License :: OSI Approved :: MIT License
Classifier: Operating System :: OS Independent
Classifier: Programming Language :: Python :: 3
Classifier: Programming Language :: Python :: 3.8
Classifier: Programming Language :: Python :: 3.9
Classifier: Programming Language :: Python :: 3.10
Classifier: Programming Language :: Python :: 3.11
Classifier: Programming Language :: Python :: 3
Classifier: Programming Language :: Python :: 3.10
Classifier: Programming Language :: Python :: 3.11
Classifier: Programming Language :: Python :: 3.8
Classifier: Programming Language :: Python :: 3.9
Project-URL: Repository, https://github.com/autoscale-app/python-agent
